{"frames": {

"俯视角走路1.png":
{
	"frame": {"x":1,"y":1,"w":257,"h":476},
	"rotated": false,
	"trimmed": false,
	"spriteSourceSize": {"x":0,"y":0,"w":257,"h":476},
	"sourceSize": {"w":257,"h":476}
},
"俯视角走路2.png":
{
	"frame": {"x":552,"y":1,"w":323,"h":440},
	"rotated": false,
	"trimmed": false,
	"spriteSourceSize": {"x":0,"y":0,"w":323,"h":440},
	"sourceSize": {"w":323,"h":440}
},
"俯视角静止.png":
{
	"frame": {"x":260,"y":1,"w":290,"h":460},
	"rotated": false,
	"trimmed": false,
	"spriteSourceSize": {"x":0,"y":0,"w":290,"h":460},
	"sourceSize": {"w":290,"h":460}
}},
"meta": {
	"app": "https://www.codeandweb.com/texturepacker",
	"version": "1.0",
	"image": "小人4.png",
	"format": "RGBA8888",
	"size": {"w":876,"h":478},
	"scale": "1",
	"smartupdate": "$TexturePacker:SmartUpdate:accb81055a7004593d191bc7bead33a1:105477cc253c64ed2bc323ef2be42e36:9592e38d1c0ef3ae072c61ea9bb74d92$"
}
}
